[{"Id":"league_chest_1","Name":"chest_carbon","PoolListId":"league_chest_1_pool","ChestRandomWeight":1,"ChestRarity":0},{"Id":"league_chest_2","Name":"chest_adamantin","PoolListId":"league_chest_2_pool","ChestRandomWeight":1,"ChestRarity":1},{"Id":"league_chest_3","Name":"chest_gold","PoolListId":"league_chest_3_pool","ChestRandomWeight":1,"ChestRarity":2},{"Id":"league_chest_4","Name":"chest_diamond","PoolListId":"league_chest_4_pool","ChestRandomWeight":1,"ChestRarity":3},{"Id":"league_bronze_1_epic","Name":"","PoolListId":"league_bronze_1_epic_pool","ChestRandomWeight":1,"ChestRarity":0},{"Id":"league_bronze_1_advanced","Name":"","PoolListId":"league_bronze_1_advanced_pool","ChestRandomWeight":1,"ChestRarity":0},{"Id":"league_bronze_1_common","Name":"","PoolListId":"league_bronze_1_common_pool","ChestRandomWeight":1,"ChestRarity":0},{"Id":"league_bronze_2_epic","Name":"","PoolListId":"league_bronze_2_epic_pool","ChestRandomWeight":1,"ChestRarity":0},{"Id":"league_bronze_2_advanced","Name":"","PoolListId":"league_bronze_2_advanced_pool","ChestRandomWeight":1,"ChestRarity":0},{"Id":"league_bronze_2_common","Name":"","PoolListId":"league_bronze_2_common_pool","ChestRandomWeight":1,"ChestRarity":0},{"Id":"league_bronze_3_epic","Name":"","PoolListId":"league_bronze_3_epic_pool","ChestRandomWeight":1,"ChestRarity":0},{"Id":"league_bronze_3_advanced","Name":"","PoolListId":"league_bronze_3_advanced_pool","ChestRandomWeight":1,"ChestRarity":0},{"Id":"league_bronze_3_common","Name":"","PoolListId":"league_bronze_3_common_pool","ChestRandomWeight":1,"ChestRarity":0},{"Id":"league_bronze_4_epic","Name":"","PoolListId":"league_bronze_4_epic_pool","ChestRandomWeight":1,"ChestRarity":0},{"Id":"league_bronze_4_advanced","Name":"","PoolListId":"league_bronze_4_advanced_pool","ChestRandomWeight":1,"ChestRarity":0},{"Id":"league_bronze_4_common","Name":"","PoolListId":"league_bronze_4_common_pool","ChestRandomWeight":1,"ChestRarity":0},{"Id":"league_bronze_5_epic","Name":"","PoolListId":"league_bronze_5_epic_pool","ChestRandomWeight":1,"ChestRarity":0},{"Id":"league_bronze_5_advanced","Name":"","PoolListId":"league_bronze_5_advanced_pool","ChestRandomWeight":1,"ChestRarity":0},{"Id":"league_bronze_5_common","Name":"","PoolListId":"league_bronze_5_common_pool","ChestRandomWeight":1,"ChestRarity":0}]